{
  "columns": 17,
  "image": "../sprites/village_home.png",
  "imageheight": 912,
  "imagewidth": 272,
  "margin": 0,
  "name": "village_home",
  "spacing": 0,
  "tilecount": 969,
  "tileheight": 16,
  "tiles": [
    {
      "id": 290,
      "properties": [
        {
          "name": "position",
          "type": "string",
          "value": "top_left"
        },
        {
          "name": "role",
          "type": "string",
          "value": "border_outer"
        },
        {
          "name": "terrain",
          "type": "string",
          "value": "grass"
        }
      ]
    },
    {
      "id": 291,
      "properties": [
        {
          "name": "position",
          "type": "string",
          "value": "top"
        },
        {
          "name": "role",
          "type": "string",
          "value": "border_outer"
        },
        {
          "name": "terrain",
          "type": "string",
          "value": "grass"
        }
      ]
    },
    {
      "id": 292,
      "properties": [
        {
          "name": "position",
          "type": "string",
          "value": "top_right"
        },
        {
          "name": "role",
          "type": "string",
          "value": "border_outer"
        },
        {
          "name": "terrain",
          "type": "string",
          "value": "grass"
        }
      ]
    },
    {
      "id": 293,
      "properties": [
        {
          "name": "position",
          "type": "string",
          "value": "top_left"
        },
        {
          "name": "role",
          "type": "string",
          "value": "border_inner"
        },
        {
          "name": "terrain",
          "type": "string",
          "value": "grass"
        }
      ]
    },
    {
      "id": 294,
      "properties": [
        {
          "name": "position",
          "type": "string",
          "value": "top_right"
        },
        {
          "name": "role",
          "type": "string",
          "value": "border_inner"
        },
        {
          "name": "terrain",
          "type": "string",
          "value": "grass"
        }
      ]
    },
    {
      "id": 307,
      "properties": [
        {
          "name": "position",
          "type": "string",
          "value": "left"
        },
        {
          "name": "role",
          "type": "string",
          "value": "border_outer"
        },
        {
          "name": "terrain",
          "type": "string",
          "value": "grass"
        }
      ]
    },
    {
      "id": 308,
      "properties": [
        {
          "name": "role",
          "type": "string",
          "value": "fill"
        },
        {
          "name": "terrain",
          "type": "string",
          "value": "grass"
        }
      ]
    },
    {
      "id": 309,
      "properties": [
        {
          "name": "position",
          "type": "string",
          "value": "right"
        },
        {
          "name": "role",
          "type": "string",
          "value": "border_outer"
        },
        {
          "name": "terrain",
          "type": "string",
          "value": "grass"
        }
      ]
    },
    {
      "id": 310,
      "properties": [
        {
          "name": "position",
          "type": "string",
          "value": "bottom_left"
        },
        {
          "name": "role",
          "type": "string",
          "value": "border_inner"
        },
        {
          "name": "terrain",
          "type": "string",
          "value": "grass"
        }
      ]
    },
    {
      "id": 311,
      "properties": [
        {
          "name": "position",
          "type": "string",
          "value": "bottom_right"
        },
        {
          "name": "role",
          "type": "string",
          "value": "border_inner"
        },
        {
          "name": "terrain",
          "type": "string",
          "value": "grass"
        }
      ]
    },
    {
      "id": 324,
      "properties": [
        {
          "name": "position",
          "type": "string",
          "value": "bottom_left"
        },
        {
          "name": "role",
          "type": "string",
          "value": "border_outer"
        },
        {
          "name": "terrain",
          "type": "string",
          "value": "grass"
        }
      ]
    },
    {
      "id": 325,
      "properties": [
        {
          "name": "position",
          "type": "string",
          "value": "bottom"
        },
        {
          "name": "role",
          "type": "string",
          "value": "border_outer"
        },
        {
          "name": "terrain",
          "type": "string",
          "value": "grass"
        }
      ]
    },
    {
      "id": 326,
      "properties": [
        {
          "name": "position",
          "type": "string",
          "value": "bottom_right"
        },
        {
          "name": "role",
          "type": "string",
          "value": "border_outer"
        },
        {
          "name": "terrain",
          "type": "string",
          "value": "grass"
        }
      ]
    },
    {
      "id": 341,
      "properties": [
        {
          "name": "position",
          "type": "string",
          "value": "top_left"
        },
        {
          "name": "role",
          "type": "string",
          "value": "border_outer"
        },
        {
          "name": "terrain",
          "type": "string",
          "value": "ground"
        }
      ]
    },
    {
      "id": 342,
      "properties": [
        {
          "name": "position",
          "type": "string",
          "value": "top"
        },
        {
          "name": "role",
          "type": "string",
          "value": "border_outer"
        },
        {
          "name": "terrain",
          "type": "string",
          "value": "ground"
        }
      ]
    },
    {
      "id": 343,
      "properties": [
        {
          "name": "position",
          "type": "string",
          "value": "top_right"
        },
        {
          "name": "role",
          "type": "string",
          "value": "border_outer"
        },
        {
          "name": "terrain",
          "type": "string",
          "value": "ground"
        }
      ]
    },
    {
      "id": 344,
      "properties": [
        {
          "name": "position",
          "type": "string",
          "value": "top_left"
        },
        {
          "name": "role",
          "type": "string",
          "value": "border_inner"
        },
        {
          "name": "terrain",
          "type": "string",
          "value": "ground"
        }
      ]
    },
    {
      "id": 345,
      "properties": [
        {
          "name": "position",
          "type": "string",
          "value": "top_right"
        },
        {
          "name": "role",
          "type": "string",
          "value": "border_inner"
        },
        {
          "name": "terrain",
          "type": "string",
          "value": "ground"
        }
      ]
    },
    {
      "id": 358,
      "properties": [
        {
          "name": "position",
          "type": "string",
          "value": "left"
        },
        {
          "name": "role",
          "type": "string",
          "value": "border_outer"
        },
        {
          "name": "terrain",
          "type": "string",
          "value": "ground"
        }
      ]
    },
    {
      "id": 359,
      "properties": [
        {
          "name": "role",
          "type": "string",
          "value": "fill"
        },
        {
          "name": "terrain",
          "type": "string",
          "value": "ground"
        }
      ]
    },
    {
      "id": 360,
      "properties": [
        {
          "name": "position",
          "type": "string",
          "value": "right"
        },
        {
          "name": "role",
          "type": "string",
          "value": "border_outer"
        },
        {
          "name": "terrain",
          "type": "string",
          "value": "ground"
        }
      ]
    },
    {
      "id": 361,
      "properties": [
        {
          "name": "position",
          "type": "string",
          "value": "bottom_left"
        },
        {
          "name": "role",
          "type": "string",
          "value": "border_inner"
        },
        {
          "name": "terrain",
          "type": "string",
          "value": "ground"
        }
      ]
    },
    {
      "id": 362,
      "properties": [
        {
          "name": "position",
          "type": "string",
          "value": "bottom_right"
        },
        {
          "name": "role",
          "type": "string",
          "value": "border_inner"
        },
        {
          "name": "terrain",
          "type": "string",
          "value": "ground"
        }
      ]
    },
    {
      "id": 375,
      "properties": [
        {
          "name": "position",
          "type": "string",
          "value": "bottom_left"
        },
        {
          "name": "role",
          "type": "string",
          "value": "border_outer"
        },
        {
          "name": "terrain",
          "type": "string",
          "value": "ground"
        }
      ]
    },
    {
      "id": 376,
      "properties": [
        {
          "name": "position",
          "type": "string",
          "value": "bottom"
        },
        {
          "name": "role",
          "type": "string",
          "value": "border_outer"
        },
        {
          "name": "terrain",
          "type": "string",
          "value": "ground"
        }
      ]
    },
    {
      "id": 377,
      "properties": [
        {
          "name": "position",
          "type": "string",
          "value": "bottom_right"
        },
        {
          "name": "role",
          "type": "string",
          "value": "border_outer"
        },
        {
          "name": "terrain",
          "type": "string",
          "value": "ground"
        }
      ]
    }
  ],
  "tilewidth": 16
}